[
    {
        "PatientAge": 353.71095608757355,
        "PatientWeigth": 971.9411706854227,
        "PatientHeigth": 1009.9199736159474
    },
    {
        "PatientAge": -66.15525552285216,
        "PatientWeigth": -197.13394481512995,
        "PatientHeigth": 33.27358983632536
    },
    {
        "PatientAge": 180.28669787729137,
        "PatientWeigth": -673.6240305576003,
        "PatientHeigth": 279.354632869364
    },
    {
        "PatientAge": 38.366191884404095,
        "PatientWeigth": 601.1051108492835,
        "PatientHeigth": -813.4072607187226
    },
    {
        "PatientAge": 176.51796594750843,
        "PatientWeigth": -338.38790376313125,
        "PatientHeigth": 825.9311945256145
    },
    {
        "PatientAge": 259.1953045316798,
        "PatientWeigth": -17.691941087771553,
        "PatientHeigth": 222.7859854090512
    },
    {
        "PatientAge": 44.674454640144965,
        "PatientWeigth": 493.03691261131127,
        "PatientHeigth": 436.70954600353355
    },
    {
        "PatientAge": 191.22033452535416,
        "PatientWeigth": 157.87854961458413,
        "PatientHeigth": -118.03899513836839
    },
    {
        "PatientAge": 158.06920537309327,
        "PatientWeigth": 1231.388829537388,
        "PatientHeigth": 2045.7784299699606
    },
    {
        "PatientAge": 93.58421170938837,
        "PatientWeigth": 334.4399427779102,
        "PatientHeigth": 373.93011312499425
    },
    {
        "PatientAge": 210.67919263218107,
        "PatientWeigth": -186.94019092370928,
        "PatientHeigth": 283.20623104451425
    },
    {
        "PatientAge": 60.33923569139475,
        "PatientWeigth": -127.06905806625822,
        "PatientHeigth": 1368.0616429275844
    },
    {
        "PatientAge": -238.4129854808645,
        "PatientWeigth": -237.6158941350219,
        "PatientHeigth": 17.86011220999299
    },
    {
        "PatientAge": -31.31695267796475,
        "PatientWeigth": 1800.736240919175,
        "PatientHeigth": 416.2489962070191
    },
    {
        "PatientAge": 78.23170598684653,
        "PatientWeigth": 433.6345741169878,
        "PatientHeigth": -721.726181409278
    },
    {
        "PatientAge": 84.88975869817796,
        "PatientWeigth": 156.16656625917523,
        "PatientHeigth": 201.58767112801993
    },
    {
        "PatientAge": 89.76200214086242,
        "PatientWeigth": 59.80277564840563,
        "PatientHeigth": 84.18844806067415
    },
    {
        "PatientAge": -55.21602264116949,
        "PatientWeigth": 6.826825351456861,
        "PatientHeigth": 571.9120531310915
    },
    {
        "PatientAge": 314.674913922739,
        "PatientWeigth": -512.2797195602884,
        "PatientHeigth": -149.80289467604425
    },
    {
        "PatientAge": -62.798628240589196,
        "PatientWeigth": -434.0453265679715,
        "PatientHeigth": 2062.3610752424474
    },
    {
        "PatientAge": 28.474780076334298,
        "PatientWeigth": 343.9110565071625,
        "PatientHeigth": 34.66166275335715
    },
    {
        "PatientAge": 106.25857136510831,
        "PatientWeigth": -560.5131341714093,
        "PatientHeigth": 1692.1960207075826
    },
    {
        "PatientAge": -126.3642916950645,
        "PatientWeigth": 375.1700056184421,
        "PatientHeigth": -453.7050876347222
    },
    {
        "PatientAge": -77.93631538738082,
        "PatientWeigth": 701.4326849505792,
        "PatientHeigth": -113.74853592709005
    },
    {
        "PatientAge": 75.38509334410979,
        "PatientWeigth": -533.9711425998697,
        "PatientHeigth": 867.3298644576843
    },
    {
        "PatientAge": 292.88657052021625,
        "PatientWeigth": 4.6787130220251925,
        "PatientHeigth": 243.78581289621002
    },
    {
        "PatientAge": -19.0590859264356,
        "PatientWeigth": 109.4723301901135,
        "PatientHeigth": -70.03985778858558
    },
    {
        "PatientAge": 69.30343890792395,
        "PatientWeigth": -54.93573379024437,
        "PatientHeigth": 397.9789916566654
    },
    {
        "PatientAge": 101.91191704180677,
        "PatientWeigth": -353.7408676759031,
        "PatientHeigth": 1622.817228824047
    },
    {
        "PatientAge": -279.3208143874529,
        "PatientWeigth": 139.55011128507118,
        "PatientHeigth": 640.3443685477687
    }
]